LICENSE
MANIFEST.in
README.md
pyproject.toml
requirements.txt
requirements_tests.txt
setup.cfg
setup.py
stochman/__init__.py
stochman/curves.py
stochman/discretized_manifold.py
stochman/geodesic.py
stochman/manifold.py
stochman/nnj.py
stochman/utils.py
stochman.egg-info/PKG-INFO
stochman.egg-info/SOURCES.txt
stochman.egg-info/dependency_links.txt
stochman.egg-info/requires.txt
stochman.egg-info/top_level.txt